bonobo/__init__.py
bonobo/__main__.py
bonobo/_api.py
bonobo/_version.py
bonobo/bonobo.svg
bonobo/constants.py
bonobo/errors.py
bonobo/registry.py
bonobo/settings.py
bonobo/commands/__init__.py
bonobo/commands/base.py
bonobo/commands/convert.py
bonobo/commands/download.py
bonobo/commands/examples.py
bonobo/commands/init.py
bonobo/commands/inspect.py
bonobo/commands/run.py
bonobo/commands/version.py
bonobo/commands/templates/bare.py-tpl
bonobo/commands/templates/default.py-tpl
bonobo/config/__init__.py
bonobo/config/configurables.py
bonobo/config/functools.py
bonobo/config/options.py
bonobo/config/processors.py
bonobo/config/services.py
bonobo/contrib/__init__.py
bonobo/contrib/django/__init__.py
bonobo/contrib/django/commands.py
bonobo/contrib/django/utils.py
bonobo/contrib/google/__init__.py
bonobo/contrib/jupyter/__init__.py
bonobo/contrib/jupyter/widget.py
bonobo/contrib/jupyter/static/extension.js
bonobo/contrib/jupyter/static/index.js
bonobo/contrib/jupyter/static/index.js.map
bonobo/contrib/opendatasoft/__init__.py
bonobo/examples/__init__.py
bonobo/examples/__main__.py
bonobo/examples/clock.py
bonobo/examples/empty.py
bonobo/examples/environ.py
bonobo/examples/datasets/__init__.py
bonobo/examples/datasets/__main__.py
bonobo/examples/datasets/coffeeshops.py
bonobo/examples/datasets/fablabs.py
bonobo/examples/files/__init__.py
bonobo/examples/files/csv_handlers.py
bonobo/examples/files/json_handlers.py
bonobo/examples/files/pickle_handlers.py
bonobo/examples/files/services.py
bonobo/examples/files/text_handlers.py
bonobo/examples/types/__init__.py
bonobo/examples/types/__main__.py
bonobo/examples/types/strings.py
bonobo/execution/__init__.py
bonobo/execution/events.py
bonobo/execution/contexts/__init__.py
bonobo/execution/contexts/base.py
bonobo/execution/contexts/graph.py
bonobo/execution/contexts/node.py
bonobo/execution/contexts/plugin.py
bonobo/execution/strategies/__init__.py
bonobo/execution/strategies/base.py
bonobo/execution/strategies/executor.py
bonobo_baseline-0.1.dist-info/LICENSE
bonobo_baseline-0.1.dist-info/METADATA
bonobo_baseline-0.1.dist-info/WHEEL
bonobo_baseline-0.1.dist-info/entry_points.txt
bonobo_baseline-0.1.dist-info/top_level.txt
bonobo_baseline-0.1.dist-info/RECORD
